drf_ember/__init__.py
drf_ember/exceptions.py
drf_ember/generics.py
drf_ember/helpers.py
drf_ember/mixins.py
drf_ember/pagination.py
drf_ember/parsers.py
drf_ember/renderers.py
drf_ember/serializers.py
drf_ember/utils/__init__.py
drf_ember/utils/api.py
drf_ember/utils/format.py
drf_ember-0.1.0b3.dist-info/DESCRIPTION.rst
drf_ember-0.1.0b3.dist-info/METADATA
drf_ember-0.1.0b3.dist-info/RECORD
drf_ember-0.1.0b3.dist-info/WHEEL
drf_ember-0.1.0b3.dist-info/metadata.json
drf_ember-0.1.0b3.dist-info/top_level.txt
