Metadata-Version: 2.0
Name: drf-ember
Version: 0.1.0b3
Summary: Enables Django REST Framework support for Ember Data's JSON API implementation.
Home-page: https://github.com/symfonico/drf-ember
Author: Julio Gonzalez Altamirano
Author-email: devjga@gmail.com
License: MIT
Keywords: ember django rest json-api framework
Platform: Any
Classifier: Development Status :: 4 - Beta
Classifier: Environment :: Web Environment
Classifier: Framework :: Django
Classifier: Intended Audience :: Developers
Classifier: License :: OSI Approved :: MIT License
Classifier: Natural Language :: English
Classifier: Operating System :: OS Independent
Classifier: Programming Language :: Python :: 3 :: Only
Classifier: Topic :: Internet :: WWW/HTTP
Classifier: Topic :: Internet :: WWW/HTTP :: HTTP Servers
Classifier: Topic :: Software Development :: Libraries :: Application Frameworks
Requires-Dist: django
Requires-Dist: djangorestframework
Requires-Dist: inflection
